Computer Architecture/HW1/cl_adder.v
module cl_adder
    #(parameter SIZE=32)
    (
    input [SIZE-1:0] input1,
    input [SIZE-1:0] input2,
    output [SIZE-1:0] result,
    output c_out);
    
    wire [SIZE:0] w_carry;
    wire [SIZE-1:0] w_generate, w_propagate, w_sum;

    assign w_carry[0] = 0;

    genvar i;
    generate
        for (i=0; i<SIZE; i=i+1)
        begin
            assign w_generate[i] = input1[i] & input2[i];
            assign w_propagate[i] = input1[i] ^ input2[i];
            assign w_carry[i+1] = w_generate[i] | (w_propagate[i] & w_carry[i]);
            assign w_sum[i] = w_carry[i] ^ w_propagate[i];
        end
    endgenerate

    assign result = w_sum;
    assign c_out = w_carry[SIZE];
endmodule

Computer Architecture/HW1/alu.v
`include "cl_adder.v"

module alu
    #(parameter SIZE=32)
    (
    input [3:0] sel,
    input [SIZE-1:0] input1,
    input [SIZE-1:0] input2,
    output reg [SIZE-1:0] alu_result,
    output reg alu_cout
    );

    wire [SIZE-1:0] add_result, sub_result;
    wire add_cout, sub_cout;
    cl_adder #(SIZE) cla_add(input1, input2, add_result, add_cout);
    cl_adder #(SIZE) cla_sub(input1, -input2, sub_result, sub_cout);

    always @(*) begin
        case (sel)
            1: alu_result = add_result;
            3: alu_result = sub_result;
            4: alu_result = input1 & input2;
            8: alu_result = input1 | input2;
            10: alu_result = input1 < input2;
            13: alu_result = ~input1;
            15: alu_result = ~(input1 | input2);
        endcase

        case (sel)
            1: alu_cout = add_cout;
            3: alu_cout = sub_cout;
            default: alu_cout = 0;
        endcase
        if (alu_result[SIZE-1]==1)
            alu_result = -alu_result;

    end
endmodule

Computer Architecture/HW1/mux.v
module mux
    #(parameter SIZE=32)
    (
    input [SIZE-1:0] in1, 
    input [SIZE-1:0] in2, 
    input sel,
    output [SIZE-1:0] out
    ); 

    assign out = (sel==0) ? in1:in2; 

endmodule

Computer Architecture/HW1/roms.v
module rom1
    #(parameter SIZE=6)
    (
    input [4:0] sel,
    output reg [SIZE-1:0] out
    );
    
    always @(*) begin
    case (sel)
        0: out = 1;
        1: out = 3;
        2: out = 4;
        3: out = 8;
        4: out = 10;
        5: out = 13;
        6: out = 15;
        7: out = 1 + 6'b010000;
        8: out = 3 + 6'b010000;
        9: out = 4 + 6'b010000;
        10: out = 8 + 6'b010000;
        11: out = 10 + 6'b010000;
        12: out = 13 + 6'b010000;
        13: out = 15 + 6'b010000;
        14: out = 1 + 6'b100000;
        15: out = 3 + 6'b100000;
        16: out = 4 + 6'b100000;
        17: out = 8 + 6'b100000;
        18: out = 10 + 6'b100000;
        19: out = 13 + 6'b100000;
        20: out = 15 + 6'b100000;
        21: out = 1 + 6'b110000;
        22: out = 3 + 6'b110000;
        23: out = 4 + 6'b110000;
        24: out = 8 + 6'b110000;
        25: out = 10 + 6'b110000;
        26: out = 13 + 6'b110000;
        27: out = 15 + 6'b110000;
    endcase
    end
endmodule

module rom2
    #(parameter SIZE=32)
    (
    input [1:0] sel,
    output reg [SIZE-1:0] out
    );
    
    always @(*) begin
    case (sel)
        0: out = 32'h00000065;
        1: out = 32'h00000054;
        2: out = 32'h00000040;
        3: out = 32'h00000082;
    endcase
    end
endmodule

module rom3
    #(parameter SIZE=32)
    (
    input [1:0] sel,
    output reg [SIZE-1:0] out
    );
    
    always @(*) begin
    case (sel)
        0: out = 32'h00000031;
        1: out = 32'h00000032;
        2: out = 32'h00000033;
        3: out = 32'h00000034;
    endcase
    end
endmodule

module rom4
    #(parameter SIZE=32)
    (
    input [1:0] sel,
    output reg [SIZE-1:0] out
    );
    
    always @(*) begin
    case (sel)
        0: out = 32'h00000041;
        1: out = 32'h00000042;
        2: out = 32'h00000043;
        3: out = 32'h00000044;
    endcase
    end
endmodule

module rom5
    #(parameter SIZE=32)
    (
    input [1:0] sel,
    output reg [SIZE-1:0] out
    );
    
    always @(*) begin
    case (sel)
        0: out = 32'h00000051;
        1: out = 32'h00000052;
        2: out = 32'h00000053;
        3: out = 32'h00000054;
    endcase
    end
endmodule

module rom6
    #(parameter SIZE=32)
    (
    input [2:0] sel,
    output reg [SIZE-1:0] out
    );
    
    always @(*) begin
    case (sel)
        0: out = 32'h97245000;
        1: out = 32'h98243000;
        2: out = 32'h99243000;
        3: out = 32'h00243000;
        4: out = 32'h01243000;
    endcase
    end
endmodule

Computer Architecture/HW1/main.v
`include "roms.v"
`include "mux.v"
`include "alu.v"


module main #(parameter SIZE=32)(
    input [4:0] rom1_in,
    input [1:0] rom2_in,
    input [1:0] rom3_in,  
    input [1:0] rom4_in,  
    input [1:0] rom5_in,  
    input [2:0] rom6_in,  
    output reg [SIZE-1:0] final_result
);
    
    wire [5:0] w_rom1_out;
    wire [SIZE-1:0] w_rom_out [2:6];


    rom1 rom_1(rom1_in, w_rom1_out);
    rom2 rom_2(rom2_in, w_rom_out[2]);
    rom3 rom_3(rom3_in, w_rom_out[3]);
    rom4 rom_4(rom4_in, w_rom_out[4]);
    rom5 rom_5(rom5_in, w_rom_out[5]);
    rom6 rom_6(rom6_in, w_rom_out[6]);

    wire [SIZE-1:0] w_mux_out [1:2];
    mux #(SIZE) mux_1(w_rom_out[2], w_rom_out[3], w_rom1_out[0], w_mux_out[1]);
    mux #(SIZE) mux_2(w_rom_out[4], w_rom_out[5], w_rom1_out[1], w_mux_out[2]);


    wire [SIZE-1:0] w_alu_result;
    wire w_alu_cout;
    alu alu_ins(w_rom1_out[5:2], w_mux_out[1], w_mux_out[2], w_alu_result, w_alu_cout);
    

    // wire w_add_cout;
    // cl_adder #(SIZE) adder(w_alu_result, w_rom_out[6], final_result, w_add_cout);

    always @(*) begin
        final_result = w_alu_result + w_rom_out[6];

        if (w_alu_result == 0)
            final_result = 32'hzzzzzzzz;
        if (w_alu_cout == 1)
            final_result = final_result + 32'h01000000;
            
    end
    // always @(rom1_in) begin
        
    // end
endmodule

Computer Architecture/HW1/main_tb.v
`include "main.v"

module main_tb ();
    parameter SIZE=32;
    reg [4:0] rom1_in;
    reg [1:0] rom2_in;
    reg [1:0] rom3_in;
    reg [1:0] rom4_in;
    reg [1:0] rom5_in;
    reg [2:0] rom6_in;
    wire [SIZE-1:0] final_result;

    main #(SIZE) main_test (rom1_in, rom2_in, rom3_in, rom4_in, rom5_in, rom6_in, final_result);

    integer i;
    initial begin
        $dumpfile("wave.vcd");
        $dumpvars(0, main_tb);
        // $monitor(rom1_sel, final_result);
        for (i=0; i<28; i=i+1) begin
            rom1_in=i;
            rom2_in=$random%4;
            rom3_in=$random%4;
            rom4_in=$random%4;
            rom5_in=$random%4;
            rom6_in=$random%5;
            #1;
        end
        rom1_in=0;
        #1;
        rom1_in=1;
        #1;
        // Note: ignore the 2 first signals, there is a delay on program
    end
endmodule

Computer Architecture/HW1/wave.vcd
$date
	Mon Nov  7 22:02:32 2022
$end
$version
	Icarus Verilog
$end
$timescale
	1s
$end
$scope module main_tb $end
$var wire 32 ! final_result [31:0] $end
$var reg 5 " rom1_in [4:0] $end
$var reg 2 # rom2_in [1:0] $end
$var reg 2 $ rom3_in [1:0] $end
$var reg 2 % rom4_in [1:0] $end
$var reg 2 & rom5_in [1:0] $end
$var reg 3 ' rom6_in [2:0] $end
$var integer 32 ( i [31:0] $end
$scope module main_test $end
$var wire 5 ) rom1_in [4:0] $end
$var wire 2 * rom2_in [1:0] $end
$var wire 2 + rom3_in [1:0] $end
$var wire 2 , rom4_in [1:0] $end
$var wire 2 - rom5_in [1:0] $end
$var wire 3 . rom6_in [2:0] $end
$var wire 6 / w_rom1_out [5:0] $end
$var wire 32 0 w_alu_result [31:0] $end
$var wire 1 1 w_alu_cout $end
$var reg 32 2 final_result [31:0] $end
$scope module alu_ins $end
$var wire 4 3 sel [3:0] $end
$var wire 32 4 sub_result [31:0] $end
$var wire 1 5 sub_cout $end
$var wire 32 6 input2 [31:0] $end
$var wire 32 7 input1 [31:0] $end
$var wire 32 8 add_result [31:0] $end
$var wire 1 9 add_cout $end
$var reg 1 1 alu_cout $end
$var reg 32 : alu_result [31:0] $end
$scope module cla_add $end
$var wire 32 ; result [31:0] $end
$var wire 32 < w_sum [31:0] $end
$var wire 32 = w_propagate [31:0] $end
$var wire 32 > w_generate [31:0] $end
$var wire 33 ? w_carry [32:0] $end
$var wire 32 @ input2 [31:0] $end
$var wire 32 A input1 [31:0] $end
$var wire 1 9 c_out $end
$scope begin genblk1[0] $end
$upscope $end
$scope begin genblk1[1] $end
$upscope $end
$scope begin genblk1[2] $end
$upscope $end
$scope begin genblk1[3] $end
$upscope $end
$scope begin genblk1[4] $end
$upscope $end
$scope begin genblk1[5] $end
$upscope $end
$scope begin genblk1[6] $end
$upscope $end
$scope begin genblk1[7] $end
$upscope $end
$scope begin genblk1[8] $end
$upscope $end
$scope begin genblk1[9] $end
$upscope $end
$scope begin genblk1[10] $end
$upscope $end
$scope begin genblk1[11] $end
$upscope $end
$scope begin genblk1[12] $end
$upscope $end
$scope begin genblk1[13] $end
$upscope $end
$scope begin genblk1[14] $end
$upscope $end
$scope begin genblk1[15] $end
$upscope $end
$scope begin genblk1[16] $end
$upscope $end
$scope begin genblk1[17] $end
$upscope $end
$scope begin genblk1[18] $end
$upscope $end
$scope begin genblk1[19] $end
$upscope $end
$scope begin genblk1[20] $end
$upscope $end
$scope begin genblk1[21] $end
$upscope $end
$scope begin genblk1[22] $end
$upscope $end
$scope begin genblk1[23] $end
$upscope $end
$scope begin genblk1[24] $end
$upscope $end
$scope begin genblk1[25] $end
$upscope $end
$scope begin genblk1[26] $end
$upscope $end
$scope begin genblk1[27] $end
$upscope $end
$scope begin genblk1[28] $end
$upscope $end
$scope begin genblk1[29] $end
$upscope $end
$scope begin genblk1[30] $end
$upscope $end
$scope begin genblk1[31] $end
$upscope $end
$upscope $end
$scope module cla_sub $end
$var wire 32 B input2 [31:0] $end
$var wire 32 C result [31:0] $end
$var wire 32 D w_sum [31:0] $end
$var wire 32 E w_propagate [31:0] $end
$var wire 32 F w_generate [31:0] $end
$var wire 33 G w_carry [32:0] $end
$var wire 32 H input1 [31:0] $end
$var wire 1 5 c_out $end
$scope begin genblk1[0] $end
$upscope $end
$scope begin genblk1[1] $end
$upscope $end
$scope begin genblk1[2] $end
$upscope $end
$scope begin genblk1[3] $end
$upscope $end
$scope begin genblk1[4] $end
$upscope $end
$scope begin genblk1[5] $end
$upscope $end
$scope begin genblk1[6] $end
$upscope $end
$scope begin genblk1[7] $end
$upscope $end
$scope begin genblk1[8] $end
$upscope $end
$scope begin genblk1[9] $end
$upscope $end
$scope begin genblk1[10] $end
$upscope $end
$scope begin genblk1[11] $end
$upscope $end
$scope begin genblk1[12] $end
$upscope $end
$scope begin genblk1[13] $end
$upscope $end
$scope begin genblk1[14] $end
$upscope $end
$scope begin genblk1[15] $end
$upscope $end
$scope begin genblk1[16] $end
$upscope $end
$scope begin genblk1[17] $end
$upscope $end
$scope begin genblk1[18] $end
$upscope $end
$scope begin genblk1[19] $end
$upscope $end
$scope begin genblk1[20] $end
$upscope $end
$scope begin genblk1[21] $end
$upscope $end
$scope begin genblk1[22] $end
$upscope $end
$scope begin genblk1[23] $end
$upscope $end
$scope begin genblk1[24] $end
$upscope $end
$scope begin genblk1[25] $end
$upscope $end
$scope begin genblk1[26] $end
$upscope $end
$scope begin genblk1[27] $end
$upscope $end
$scope begin genblk1[28] $end
$upscope $end
$scope begin genblk1[29] $end
$upscope $end
$scope begin genblk1[30] $end
$upscope $end
$scope begin genblk1[31] $end
$upscope $end
$upscope $end
$upscope $end
$scope module mux_1 $end
$var wire 1 I sel $end
$var wire 32 J out [31:0] $end
$var wire 32 K in2 [31:0] $end
$var wire 32 L in1 [31:0] $end
$upscope $end
$scope module mux_2 $end
$var wire 1 M sel $end
$var wire 32 N out [31:0] $end
$var wire 32 O in2 [31:0] $end
$var wire 32 P in1 [31:0] $end
$upscope $end
$scope module rom_1 $end
$var wire 5 Q sel [4:0] $end
$var reg 6 R out [5:0] $end
$upscope $end
$scope module rom_2 $end
$var wire 2 S sel [1:0] $end
$var reg 32 T out [31:0] $end
$upscope $end
$scope module rom_3 $end
$var wire 2 U sel [1:0] $end
$var reg 32 V out [31:0] $end
$upscope $end
$scope module rom_4 $end
$var wire 2 W sel [1:0] $end
$var reg 32 X out [31:0] $end
$upscope $end
$scope module rom_5 $end
$var wire 2 Y sel [1:0] $end
$var reg 32 Z out [31:0] $end
$upscope $end
$scope module rom_6 $end
$var wire 3 [ sel [2:0] $end
$var reg 32 \ out [31:0] $end
$upscope $end
$upscope $end
$upscope $end
$enddefinitions $end
#0
$dumpvars
b10011001001001000011000000000000 \
b10 [
b1010100 Z
b11 Y
b1000010 X
b1 W
b110010 V
b1 U
b1100101 T
b0 S
b1 R
b0 Q
b1000010 P
b1010100 O
b1000010 N
0M
b1100101 L
b110010 K
b110010 J
1I
b110010 H
b1111100 G
b110010 F
b11111111111111111111111110001100 E
b11111111111111111111111111110000 D
b11111111111111111111111111110000 C
b11111111111111111111111110111110 B
b110010 A
b1000010 @
b100 ?
b10 >
b1110000 =
b1110100 <
b1110100 ;
bx :
09
b1110100 8
b110010 7
b1000010 6
05
b11111111111111111111111111110000 4
b0 3
bx 2
01
bx 0
b1 /
b10 .
b11 -
b1 ,
b1 +
b0 *
b0 )
b0 (
b10 '
b11 &
b1 %
b1 $
b0 #
b0 "
bx !
$end
#1
b10000100 8
b10000100 ;
b10000100 <
b11100100 ?
b11111111111111111111111111100000 4
b11111111111111111111111111100000 C
b11111111111111111111111111100000 D
b1100000 =
b10010 >
b100010 F
b11111111111111111111111110011100 E
b11111111111111111111111110101110 B
b1010010 6
b1010010 @
b1010010 N
1M
b1001001000011000000000000 \
b1010010 O
b1010010 Z
b1000011 P
b1000011 X
b1010100 L
b1010100 T
b11 /
b11 R
b100 '
b100 .
b100 [
b1 &
b1 -
b1 Y
b10 %
b10 ,
b10 W
b1 #
b1 *
b1 S
b1 "
b1 )
b1 Q
b1 (
#2
05
b11111111111111111111111111111110 4
b11111111111111111111111111111110 C
b11111111111111111111111111111110 D
b0 G
b10000010 8
b10000010 ;
b10000010 <
b10000000 ?
b11111111111111111111111111111110 E
b0 F
b10 =
b1000000 >
b1001001000011000010000010 !
b1001001000011000010000010 2
b10000010 0
b10000010 :
b1000000 7
b1000000 A
b1000000 H
b1000000 J
b11111111111111111111111110111110 B
b1000010 6
b1000010 @
b1000010 N
b1 3
0M
0I
b1010001 O
b1010001 Z
b1000010 P
b1000010 X
b1000000 L
b1000000 T
b100 /
b100 R
b0 &
b0 -
b0 Y
b1 %
b1 ,
b1 W
b10 #
b10 *
b10 S
b10 "
b10 )
b10 Q
b10 (
#3
b10000011 8
b10000011 ;
b10000011 <
b11111111111111111111111111111101 4
b11111111111111111111111111111101 C
b11111111111111111111111111111101 D
b11 =
b11111111111111111111111111111101 E
b11111111111111111111111110111101 B
b1000011 6
b1000011 @
b1000011 N
b10 3
b1010010 O
b1010010 Z
b1000011 P
b1000011 X
b1000 /
b1000 R
b111 '
b111 .
b111 [
b1 &
b1 -
b1 Y
b10 %
b10 ,
b10 W
b11 "
b11 )
b11 Q
b11 (
#4
b10010011 8
b10010011 ;
b10010011 <
b11111111111111111111111111101101 4
b11111111111111111111111111101101 C
b11111111111111111111111111101101 D
b10011 =
b11111111111111111111111111101101 E
b11111111111111111111111110101101 B
b1010011 6
b1010011 @
b1010011 N
1M
b1010011 O
b1010011 Z
b110100 K
b110100 V
b1010 /
b1010 R
b101 '
b101 .
b101 [
b10 &
b10 -
b10 Y
b11 $
b11 +
b11 U
b100 "
b100 )
b100 Q
b100 (
#5
b11111111111111111111111111101111 4
b11111111111111111111111111101111 C
b11111111111111111111111111101111 D
b1100000 G
b0 ?
b1110011 8
b1110011 ;
b1110011 <
b11111111111111111111111110001111 E
b110000 F
b0 >
b1110011 =
b1001001000011000000010001 !
b1001001000011000000010001 2
b10001 0
b10001 :
b11111111111111111111111110111110 B
b1000010 6
b1000010 @
b1000010 N
b110001 7
b110001 A
b110001 H
b110001 J
b11 3
0M
1I
b1010010 O
b1010010 Z
b1000010 P
b1000010 X
b110001 K
b110001 V
b1010100 L
b1010100 T
b1101 /
b1101 R
b110 '
b110 .
b110 [
b1 &
b1 -
b1 Y
b1 %
b1 ,
b1 W
b0 $
b0 +
b0 U
b1 #
b1 *
b1 S
b101 "
b101 )
b101 Q
b101 (
#6
b1001001000011000000011110 !
b1001001000011000000011110 2
b10000100 8
b10000100 ;
b10000100 <
b11100110 ?
b11111111111111111111111111100010 4
b11111111111111111111111111100010 C
b11111111111111111111111111100010 D
b1111110 G
b1100010 =
b10001 >
b11111111111111111111111110011100 E
b100011 F
b11110 0
b11110 :
b11111111111111111111111110101111 B
b1010001 6
b1010001 @
b1010001 N
b110011 7
b110011 A
b110011 H
b110011 J
1M
b1010001 O
b1010001 Z
b1000001 P
b1000001 X
b110011 K
b110011 V
b10000010 L
b10000010 T
b1111 /
b1111 R
b100 '
b100 .
b100 [
b0 &
b0 -
b0 Y
b0 %
b0 ,
b0 W
b10 $
b10 +
b10 U
b11 #
b11 *
b11 S
b110 "
b110 )
b110 Q
b110 (
#7
b1110111 8
b1110111 ;
b1110111 <
b0 ?
b1100000 G
b11111111111111111111111111101111 4
b11111111111111111111111111101111 C
b11111111111111111111111111101111 D
b1110111 =
b0 >
b110000 F
b11111111111111111111111110001111 E
bz !
bz 2
b0 0
b0 :
b11111111111111111111111110111100 B
b1000100 6
b1000100 @
b1000100 N
b100 3
0M
b1010010 O
b1010010 Z
b1000100 P
b1000100 X
b1010100 L
b1010100 T
b10001 /
b10001 R
b101 '
b101 .
b101 [
b1 &
b1 -
b1 Y
b11 %
b11 ,
b11 W
b1 #
b1 *
b1 S
b111 "
b111 )
b111 Q
b111 (
#8
b10000101 8
b10000101 ;
b10000101 <
b11100100 ?
b1000000 G
b11111111111111111111111111011111 4
b11111111111111111111111111011111 C
b11111111111111111111111111011111 D
b1100001 =
b10010 >
b100000 F
b11111111111111111111111110011111 E
b10010 0
b10010 :
b11111111111111111111111110101101 B
b1010011 6
b1010011 @
b1010011 N
b110010 7
b110010 A
b110010 H
b110010 J
b10011000001001000011000000010010 !
b10011000001001000011000000010010 2
1M
b10011000001001000011000000000000 \
b1010011 O
b1010011 Z
b1000011 P
b1000011 X
b110010 K
b110010 V
b10000010 L
b10000010 T
b10011 /
b10011 R
b1 '
b1 .
b1 [
b10 &
b10 -
b10 Y
b10 %
b10 ,
b10 W
b1 $
b1 +
b1 U
b11 #
b11 *
b11 S
b1000 "
b1000 )
b1000 Q
b1000 (
#9
15
b111111 4
b111111 C
b111111 D
b111111111111111111111111100000000 G
b11000101 8
b11000101 ;
b11000101 <
b100 ?
b11111111111111111111111100111111 E
b10000000 F
b11000001 =
b10 >
b11111111111111111111111110111101 B
b1000011 6
b1000011 @
b1000011 N
b10000010 7
b10000010 A
b10000010 H
b10000010 J
b101 3
0M
0I
b110100 K
b110100 V
b10100 /
b10100 R
b101 '
b101 .
b101 [
b11 $
b11 +
b11 U
b1001 "
b1001 )
b1001 Q
b1001 (
#10
05
b0 G
b11111111111111111111111111111110 4
b11111111111111111111111111111110 C
b11111111111111111111111111111110 D
b10000010 8
b10000010 ;
b10000010 <
b10000000 ?
b0 F
b11111111111111111111111111111110 E
b10 =
b1000000 >
b11111111111111111111111110111110 B
b1000010 6
b1000010 @
b1000010 N
b1000000 7
b1000000 A
b1000000 H
b1000000 J
b10010111001001000101000000010010 !
b10010111001001000101000000010010 2
b110 3
b10010111001001000101000000000000 \
b1010001 O
b1010001 Z
b1000010 P
b1000010 X
b110011 K
b110011 V
b1000000 L
b1000000 T
b11000 /
b11000 R
b0 '
b0 .
b0 [
b0 &
b0 -
b0 Y
b1 %
b1 ,
b1 W
b10 $
b10 +
b10 U
b10 #
b10 *
b10 S
b1010 "
b1010 )
b1010 Q
b1010 (
#11
15
b1 4
b1 C
b1 D
b111111111111111111111111111111000 G
b10100000 ?
b10100111 8
b10100111 ;
b10100111 <
b11111111111111111111111111111001 E
b100 F
b1010000 >
b111 =
b11111111111111111111111110101101 B
b1010011 6
b1010011 @
b1010011 N
b1010100 7
b1010100 A
b1010100 H
b1010100 J
b10011000001001000011000000010010 !
b10011000001001000011000000010010 2
1M
b10011000001001000011000000000000 \
b1010011 O
b1010011 Z
b1000011 P
b1000011 X
b110100 K
b110100 V
b1010100 L
b1010100 T
b11010 /
b11010 R
b1 '
b1 .
b1 [
b10 &
b10 -
b10 Y
b10 %
b10 ,
b10 W
b11 $
b11 +
b11 U
b1 #
b1 *
b1 S
b1011 "
b1011 )
b1011 Q
b1011 (
#12
05
b1100000 G
b11111111111111111111111111101111 4
b11111111111111111111111111101111 C
b11111111111111111111111111101111 D
b0 ?
b1110111 8
b1110111 ;
b1110111 <
b110000 F
b11111111111111111111111110001111 E
b0 >
b1110111 =
b11111111111111111111111110111100 B
b1000100 6
b1000100 @
b1000100 N
b110011 7
b110011 A
b110011 H
b110011 J
b111 3
0M
1I
b1010010 O
b1010010 Z
b1000100 P
b1000100 X
b110011 K
b110011 V
b1100101 L
b1100101 T
b11101 /
b11101 R
b1 &
b1 -
b1 Y
b11 %
b11 ,
b11 W
b10 $
b10 +
b10 U
b0 #
b0 *
b0 S
b1100 "
b1100 )
b1100 Q
b1100 (
#13
b10000111 8
b10000111 ;
b10000111 <
b11100000 ?
b1111000 G
b11111111111111111111111111100001 4
b11111111111111111111111111100001 C
b11111111111111111111111111100001 D
b1100111 =
b10000 >
b100100 F
b11111111111111111111111110011001 E
b11111111111111111111111110101101 B
b1010011 6
b1010011 @
b1010011 N
b110100 7
b110100 A
b110100 H
b110100 J
1M
b1010011 O
b1010011 Z
b1000011 P
b1000011 X
b110100 K
b110100 V
b10000010 L
b10000010 T
b11111 /
b11111 R
b10 &
b10 -
b10 Y
b10 %
b10 ,
b10 W
b11 $
b11 +
b11 U
b11 #
b11 *
b11 S
b1101 "
b1101 )
b1101 Q
b1101 (
#14
b1100000 G
b11111111111111111111111111101111 4
b11111111111111111111111111101111 C
b11111111111111111111111111101111 D
b1110101 8
b1110101 ;
b1110101 <
b100 ?
b110000 F
b11111111111111111111111110001111 E
b1110001 =
b10 >
b1110011 0
b1110011 :
b11111111111111111111111110111101 B
b1000011 6
b1000011 @
b1000011 N
b110010 7
b110010 A
b110010 H
b110010 J
b1001001000011000001110011 !
b1001001000011000001110011 2
b1000 3
0M
b1001001000011000000000000 \
b1010001 O
b1010001 Z
b110010 K
b110010 V
b1010100 L
b1010100 T
b100001 /
b100001 R
b100 '
b100 .
b100 [
b0 &
b0 -
b0 Y
b1 $
b1 +
b1 U
b1 #
b1 *
b1 S
b1110 "
b1110 )
b1110 Q
b1110 (
#15
b10000101 8
b10000101 ;
b10000101 <
b1000000 G
b11111111111111111111111111011101 4
b11111111111111111111111111011101 C
b11111111111111111111111111011101 D
b11100000 ?
b1100101 =
b100000 F
b11111111111111111111111110011101 E
b10000 >
b1001001000011000001110101 !
b1001001000011000001110101 2
b1110101 0
b1110101 :
b11111111111111111111111110101100 B
b1010100 6
b1010100 @
b1010100 N
b110001 7
b110001 A
b110001 H
b110001 J
1M
b1010100 O
b1010100 Z
b1000100 P
b1000100 X
b110001 K
b110001 V
b10000010 L
b10000010 T
b100011 /
b100011 R
b110 '
b110 .
b110 [
b11 &
b11 -
b11 Y
b11 %
b11 ,
b11 W
b0 $
b0 +
b0 U
b11 #
b11 *
b11 S
b1111 "
b1111 )
b1111 Q
b1111 (
#16
15
b111111111111111111111111101111100 G
b1000000 4
b1000000 C
b1000000 D
b100 ?
b11000100 8
b11000100 ;
b11000100 <
b10000010 F
b11111111111111111111111100111100 E
b10 >
b11000000 =
b11111111111111111111111110111110 B
b1000010 6
b1000010 @
b1000010 N
b10000010 7
b10000010 A
b10000010 H
b10000010 J
b10010111001001000101000001110101 !
b10010111001001000101000001110101 2
b1001 3
0M
0I
b10010111001001000101000000000000 \
b1010001 O
b1010001 Z
b1000010 P
b1000010 X
b110010 K
b110010 V
b100100 /
b100100 R
b0 '
b0 .
b0 [
b0 &
b0 -
b0 Y
b1 %
b1 ,
b1 W
b1 $
b1 +
b1 U
b10000 "
b10000 )
b10000 Q
b10000 (
#17
15
b10011 4
b10011 C
b10011 D
b111111111111111111111111111111000 G
b10010101 8
b10010101 ;
b10010101 <
b10000000 ?
b11111111111111111111111111101011 E
b10100 F
b10101 =
b1000000 >
b0 0
b0 :
b11111111111111111111111110111111 B
b1000001 6
b1000001 @
b1000001 N
b1010100 7
b1010100 A
b1010100 H
b1010100 J
bz !
bz 2
b1010 3
b1001001000011000000000000 \
b1010011 O
b1010011 Z
b1000001 P
b1000001 X
b110011 K
b110011 V
b1010100 L
b1010100 T
b101000 /
b101000 R
b100 '
b100 .
b100 [
b10 &
b10 -
b10 Y
b0 %
b0 ,
b0 W
b10 $
b10 +
b10 U
b1 #
b1 *
b1 S
b10001 "
b10001 )
b10001 Q
b10001 (
#18
b101111 4
b101111 C
b101111 D
b111111111111111111111111100000000 G
b11010101 8
b11010101 ;
b11010101 <
b100 ?
b11111111111111111111111100101111 E
b10000000 F
b11010001 =
b10 >
b11111111111111111111111110101101 B
b1010011 6
b1010011 @
b1010011 N
b10000010 7
b10000010 A
b10000010 H
b10000010 J
bz !
bz 2
1M
b10011000001001000011000000000000 \
b1000011 P
b1000011 X
b110010 K
b110010 V
b10000010 L
b10000010 T
b101010 /
b101010 R
b1 '
b1 .
b1 [
b10 %
b10 ,
b10 W
b1 $
b1 +
b1 U
b11 #
b11 *
b11 S
b10010 "
b10010 )
b10010 Q
b10010 (
#19
05
b1111000 G
b11111111111111111111111111110000 4
b11111111111111111111111111110000 C
b11111111111111111111111111110000 D
b1111000 8
b1111000 ;
b1111000 <
b1000 ?
b110100 F
b11111111111111111111111110001000 E
b1110000 =
b100 >
b11111111111111111111111110111100 B
b1000100 6
b1000100 @
b1000100 N
b110100 7
b110100 A
b110100 H
b110100 J
bz !
bz 2
b1011 3
0M
1I
b1010010 O
b1010010 Z
b1000100 P
b1000100 X
b110100 K
b110100 V
b1010100 L
b1010100 T
b101101 /
b101101 R
b110 '
b110 .
b110 [
b1 &
b1 -
b1 Y
b11 %
b11 ,
b11 W
b11 $
b11 +
b11 U
b1 #
b1 *
b1 S
b10011 "
b10011 )
b10011 Q
b10011 (
#20
b10000101 8
b10000101 ;
b10000101 <
b1000000 G
b11111111111111111111111111011111 4
b11111111111111111111111111011111 C
b11111111111111111111111111011111 D
b11100100 ?
b1100001 =
b100000 F
b11111111111111111111111110011111 E
b10010 >
b11111111111111111111111110101101 B
b1010011 6
b1010011 @
b1010011 N
b110010 7
b110010 A
b110010 H
b110010 J
bz !
bz 2
1M
b10011001001001000011000000000000 \
b1010011 O
b1010011 Z
b110010 K
b110010 V
b10000010 L
b10000010 T
b101111 /
b101111 R
b10 '
b10 .
b10 [
b10 &
b10 -
b10 Y
b1 $
b1 +
b1 U
b11 #
b11 *
b11 S
b10100 "
b10100 )
b10100 Q
b10100 (
#21
b11111111111111111111111111110010 4
b11111111111111111111111111110010 C
b11111111111111111111111111110010 D
b1111110 G
b1110100 8
b1110100 ;
b1110100 <
b110 ?
b11111111111111111111111110001100 E
b110011 F
b1110010 =
b1 >
b11111111111111111111111110111111 B
b1000001 6
b1000001 @
b1000001 N
b110011 7
b110011 A
b110011 H
b110011 J
bz !
bz 2
b1100 3
0M
b1000001 P
b1000001 X
b110011 K
b110011 V
b1000000 L
b1000000 T
b110001 /
b110001 R
b101 '
b101 .
b101 [
b0 %
b0 ,
b0 W
b10 $
b10 +
b10 U
b10 #
b10 *
b10 S
b10101 "
b10101 )
b10101 Q
b10101 (
#22
b11111111111111111111111111100000 4
b11111111111111111111111111100000 C
b11111111111111111111111111100000 D
b1111000 G
b10001000 8
b10001000 ;
b10001000 <
b11101000 ?
b11111111111111111111111110011000 E
b100100 F
b1100000 =
b10100 >
b11111111111111111111111110101100 B
b1010100 6
b1010100 @
b1010100 N
b110100 7
b110100 A
b110100 H
b110100 J
bz !
bz 2
1M
b1001001000011000000000000 \
b1010100 O
b1010100 Z
b1000100 P
b1000100 X
b110100 K
b110100 V
b10000010 L
b10000010 T
b110011 /
b110011 R
b100 '
b100 .
b100 [
b11 &
b11 -
b11 Y
b11 %
b11 ,
b11 W
b11 $
b11 +
b11 U
b11 #
b11 *
b11 S
b10110 "
b10110 )
b10110 Q
b10110 (
#23
15
b111111111111111111111111111111000 G
b100001 4
b100001 C
b100001 D
b10101001 8
b10101001 ;
b10101001 <
b10001000 ?
b11111111111111111111111111011001 E
b100001 =
b1000100 >
b1100110 0
b1100110 :
b1100101 7
b1100101 A
b1100101 H
b1100101 J
b11111111111111111111111110111100 B
b1000100 6
b1000100 @
b1000100 N
b1001001000011000001100110 !
b1001001000011000001100110 2
b1101 3
0M
0I
b1010011 O
b1010011 Z
b1100101 L
b1100101 T
b110100 /
b110100 R
b10 &
b10 -
b10 Y
b0 #
b0 *
b0 S
b10111 "
b10111 )
b10111 Q
b10111 (
#24
15
b10000000 ?
b111111111111111111111111111111000 G
b10001 4
b10001 C
b10001 D
b10010111 8
b10010111 ;
b10010111 <
b1000000 >
b11111111111111111111111111101001 E
b10100 F
b10111 =
b11111111111111111111111110111101 B
b1000011 6
b1000011 @
b1000011 N
b1010100 7
b1010100 A
b1010100 H
b1010100 J
b1110 3
b1010010 O
b1010010 Z
b1000011 P
b1000011 X
b110010 K
b110010 V
b1010100 L
b1010100 T
b111000 /
b111000 R
b101 '
b101 .
b101 [
b1 &
b1 -
b1 Y
b10 %
b10 ,
b10 W
b1 $
b1 +
b1 U
b1 #
b1 *
b1 S
b11000 "
b11000 )
b11000 Q
b11000 (
