Computer Architecture/State Machines/1000001 sequence detector (overlapping)/q1.v
module q1 (clk, reset, in, out);
    input clk, reset, in;
    output out;
    reg out;
    reg [2:0] state;
    reg [2:0] next_state;

    initial begin
        state = 0;
    end

    always @(posedge clk) begin
        if(reset) state = 0;
        else state = next_state;
    end

    always @(state, in) begin
        out = 0;
        next_state = 0;
        case(state)
            0: begin
                if(in) next_state = 1;
                else next_state = 0;
            end
            1: begin
                if(in) next_state = 1;
                else next_state = 2;
            end
            2: begin
                if(in) next_state = 1;
                else next_state = 3;
            end
            3: begin
                if(in) next_state = 1;
                else next_state = 4;
            end
            4: begin
                if(in) next_state = 1;
                else next_state = 5;
            end
            5: begin
                if(in) next_state = 1;
                else next_state = 6;
            end
            6: begin
                if(in) next_state = 7;
                else next_state = 0;
            end
            7: begin
                out = 1;
                if(in) next_state = 1;
                else next_state = 2;
            end
            default: begin
                next_state = 0;
            end
        endcase
    end

endmodule

Computer Architecture/State Machines/1000001 sequence detector (overlapping)/q1_tb.v
`include "q1.v"

module q1_tb();
    reg clk, reset, in;
    wire out;

    q1 qtb(
        .clk(clk),
        .reset(reset),
        .in(in),
        .out(out)
    );

    initial begin
        $dumpfile("wave.vcd");
        $dumpvars(0, q1_tb);
        reset = 1;
        in = 0;
        #10;
        reset = 0;
        #10;
        in = 1;
        #10;
        in = 0;
        #10;
        in = 0;
        #10;
        in = 0;
        #10;
        in = 0;
        #10;
        in = 0;
        #10;
        in = 1;
        #10;
        in = 0;
        #10;
        in = 0;
        #10;
        in = 0;
        #10;
        in = 0;
        #10;
        in = 0;
        #10;
        in = 1;
        #10;
        in = 0;
        #10;
        in = 1;
        #10;
        in = 1;
        #10;
        in = 1;
        #10;
        in = 0;
        #10;
        in = 0;
        #10;
        in = 0;
        #10;
        in = 0;
        #10;
        in = 0;
        #10;
        in = 1;
        #10;
        in = 1;
        #10;
        in = 1;
        #10;
        $finish;
    end

    always 
        #5 clk = ~clk;
    initial
        clk = 0;
endmodule

Computer Architecture/State Machines/1000001 sequence detector (overlapping)/wave.vcd
$date
	Sat Dec 24 21:28:36 2022
$end
$version
	Icarus Verilog
$end
$timescale
	1s
$end
$scope module q1_tb $end
$var wire 1 ! out $end
$var reg 1 " clk $end
$var reg 1 # in $end
$var reg 1 $ reset $end
$scope module qtb $end
$var wire 1 " clk $end
$var wire 1 # in $end
$var wire 1 $ reset $end
$var reg 3 % next_state [2:0] $end
$var reg 1 ! out $end
$var reg 3 & state [2:0] $end
$upscope $end
$upscope $end
$enddefinitions $end
#0
$dumpvars
b0 &
b0 %
1$
0#
0"
0!
$end
#5
1"
#10
0"
0$
#15
1"
#20
b1 %
0"
1#
#25
b1 %
b1 &
1"
#30
b10 %
0"
0#
#35
b11 %
b10 &
1"
#40
0"
#45
b100 %
b11 &
1"
#50
0"
#55
b101 %
b100 &
1"
#60
0"
#65
b110 %
b101 &
1"
#70
0"
#75
b0 %
b110 &
1"
#80
b111 %
0"
1#
#85
1!
b1 %
b111 &
1"
#90
b10 %
1!
0"
0#
#95
b11 %
0!
b10 &
1"
#100
0"
#105
b100 %
b11 &
1"
#110
0"
#115
b101 %
b100 &
1"
#120
0"
#125
b110 %
b101 &
1"
#130
0"
#135
b0 %
b110 &
1"
#140
b111 %
0"
1#
#145
1!
b1 %
b111 &
1"
#150
b10 %
1!
0"
0#
#155
b11 %
0!
b10 &
1"
#160
b1 %
0"
1#
#165
b1 %
b1 &
1"
#170
0"
#175
1"
#180
0"
#185
1"
#190
b10 %
0"
0#
#195
b11 %
b10 &
1"
#200
0"
#205
b100 %
b11 &
1"
#210
0"
#215
b101 %
b100 &
1"
#220
0"
#225
b110 %
b101 &
1"
#230
0"
#235
b0 %
b110 &
1"
#240
b111 %
0"
1#
#245
1!
b1 %
b111 &
1"
#250
0"
#255
b1 %
0!
b1 &
1"
