Lab/ALU/alu.v
module alu
    #(parameter SIZE=8)
    (
    input [3:0] op,
    input [SIZE-1:0] a,
    input [SIZE-1:0] b,
    output reg [SIZE-1:0] result,
    output reg cout,
    output reg ov,
    output reg sign
    );

    always @(*) begin
        // if(input1[SIZE-1]==1){
        //     reg [SIZE-1:0] a = -(~input1[SIZE-1:0]+1);
        // }
        // if(input2[SIZE-1]==1){
        //     reg [SIZE-1:0] b = -(~input2[SIZE-1:0]+1);
        // }
        // reg [SIZE-1:0] a,
        // reg [SIZE-1:0] b,
        // a=input1;
        // b=input2;
        case (op)
            0: {cout, result} = a + b;
            1: {cout, result} = a - b;
            2: {cout, result} = a & b;
            3: {cout, result} = a | b;
            4: {cout, result} = a ^ b;
            5: {cout, result} = ~ a;
            6: {cout, result} = a >> 1;
            7: {cout, result} = a << 1;
        endcase

        if((a[SIZE-1]==1 && b[SIZE-1]==1 && result[SIZE-1]==0) || (a[SIZE-1]==0 && b[SIZE-1]==0 && result[SIZE-1]==1)) begin
            ov=1;
        end
        else begin
            ov=0;
        end

        sign=result[SIZE-1];
        
    end
endmodule

Lab/ALU/alu_tb.v
`include "alu.v"

module alu_tb();
    parameter SIZE = 8;

    reg [3:0] op;
    reg [SIZE-1:0] a;
    reg [SIZE-1:0] b;
    wire [SIZE-1:0] result;
    wire cout, ov, sign;

    alu #(SIZE) alu_instance(
        .op(op),
        .a(a),
        .b(b),
        .result(result),
        .cout(cout),
        .ov(ov),
        .sign(sign)
    );

    integer i;
    initial begin
        $dumpfile("wave.vcd");
        $dumpvars(0, alu_tb);
        op=0;
        a=8'b10000000;
        b=8'b10000001;
        #10;
        a=8'b01111111;
        b=8'b00000011;
        #10;
        a=8'b01111111;
        b=8'b10000011;
        #10;
        op=1;
        a=8'b01111111;
        b=8'b10000001;
        #10;
        a=8'b10000000;
        b=8'b10000001;
        #10;
        a=8'b01111111;
        b=8'b00000011;
        #10
        op=2;
        #10;
        op=3;
        #10;
        op=4;
        #10;
        op=5;
        #10;
        op=6;
        #10;
        op=7;
        #10;
    end
    
endmodule

Lab/ALU/wave.vcd
$date
	Sat Nov 12 20:56:39 2022
$end
$version
	Icarus Verilog
$end
$timescale
	1s
$end
$scope module alu_tb $end
$var wire 1 ! sign $end
$var wire 8 " result [7:0] $end
$var wire 1 # ov $end
$var wire 1 $ cout $end
$var reg 8 % a [7:0] $end
$var reg 8 & b [7:0] $end
$var reg 4 ' op [3:0] $end
$scope module alu_instance $end
$var wire 8 ( a [7:0] $end
$var wire 8 ) b [7:0] $end
$var wire 4 * op [3:0] $end
$var reg 1 $ cout $end
$var reg 1 # ov $end
$var reg 8 + result [7:0] $end
$var reg 1 ! sign $end
$upscope $end
$upscope $end
$enddefinitions $end
#0
$dumpvars
b1 +
b0 *
b10000001 )
b10000000 (
b0 '
b10000001 &
b10000000 %
1$
1#
b1 "
0!
$end
#10
1!
0$
b10000010 "
b10000010 +
b11 &
b11 )
b1111111 %
b1111111 (
#20
0!
0#
1$
b10 "
b10 +
b10000011 &
b10000011 )
#30
1!
b11111110 "
b11111110 +
b10000001 &
b10000001 )
b1 '
b1 *
#40
b11111111 "
b11111111 +
b10000000 %
b10000000 (
#50
0!
0$
b1111100 "
b1111100 +
b11 &
b11 )
b1111111 %
b1111111 (
#60
b11 "
b11 +
b10 '
b10 *
#70
b1111111 "
b1111111 +
b11 '
b11 *
#80
b1111100 "
b1111100 +
b100 '
b100 *
#90
1!
1#
1$
b10000000 "
b10000000 +
b101 '
b101 *
#100
0!
0#
0$
b111111 "
b111111 +
b110 '
b110 *
#110
1!
1#
b11111110 "
b11111110 +
b111 '
b111 *
